.gitignore
.readthedocs.yml
CHANGES.rst
LICENSE
README.rst
environment.yml
pyproject.toml
setup.cfg
setup.py
.github/workflows/ci.yml
docs/Makefile
docs/api.rst
docs/conf.py
docs/index.rst
docs/make.bat
docs/_static/custom.css
docs/images/gappy-logo.svg
docs/images/gappy-logo.svg.png
gappy/__init__.py
gappy/_version.py
gappy/conftest.py
gappy/context_managers.py
gappy/core.pxd
gappy/core.pyx
gappy/exceptions.py
gappy/gap_functions.py
gappy/gap_globals.py
gappy/gap_includes.pxd
gappy/gapobj.pxd
gappy/gapobj.pyx
gappy/gmp.pxd
gappy/operations.py
gappy/utils.pyx
gappy/version.py
gappy/_dev/__init__.py
gappy/_dev/scm_version.py
gappy_system.egg-info/PKG-INFO
gappy_system.egg-info/SOURCES.txt
gappy_system.egg-info/dependency_links.txt
gappy_system.egg-info/requires.txt
gappy_system.egg-info/top_level.txt
tests/conftest.py
tests/test_long.py
tests/test_misc.py