Metadata-Version: 2.1
Name: gappy-system
Version: 0.1.0a2
Summary: Python interface to GAP
Home-page: https://github.com/embray/gappy
Author: E. Madison Bray
Author-email: embray@lri.fr
License: GPLv3+
Platform: linux
Classifier: Development Status :: 3 - Alpha
Classifier: Intended Audience :: Education
Classifier: Intended Audience :: Science/Research
Classifier: License :: OSI Approved :: GNU General Public License v3 or later (GPLv3+)
Classifier: Operating System :: POSIX :: Linux
Classifier: Programming Language :: Cython
Classifier: Programming Language :: Python :: 3.6
Classifier: Programming Language :: Python :: 3.7
Classifier: Programming Language :: Python :: 3.8
Classifier: Topic :: Scientific/Engineering :: Mathematics
Requires-Python: >=3.6
Provides-Extra: tests
Provides-Extra: docs
